src/__init__.py
src/data/__init__.py
src/data/make_dataset.py
src/entities/__init__.py
src/entities/data_params.py
src/entities/params.py
src/entities/train_params.py
src/models/__init__.py
src/models/inference.py
src/models/train.py
shockless_hw_5_prj-0.1.0.dist-info/LICENSE
shockless_hw_5_prj-0.1.0.dist-info/METADATA
shockless_hw_5_prj-0.1.0.dist-info/WHEEL
shockless_hw_5_prj-0.1.0.dist-info/top_level.txt
shockless_hw_5_prj-0.1.0.dist-info/RECORD
