Metadata-Version: 2.1
Name: shockless-hw-5-prj
Version: 0.1.0
Summary: Репозиторий курса MLOps
Author: Fedor Avilov
License: MIT
License-File: LICENSE
